oskui/__init__.py
oskui/visual.py
oskui-0.14.1.dist-info/LICENSE
oskui-0.14.1.dist-info/METADATA
oskui-0.14.1.dist-info/WHEEL
oskui-0.14.1.dist-info/top_level.txt
oskui-0.14.1.dist-info/RECORD
