Metadata-Version: 2.1
Name: oskui
Version: 0.14.1
Summary: Set of command line user interface tools
Home-page: https://github.com/Wing0/oskui
Author: Oskari Vinko
Author-email: oskari.vinko@gmail.com
License: MIT
Download-URL: https://github.com/Wing0/oskui/archive/0.14.1.tar.gz
Platform: UNKNOWN
License-File: LICENSE
